xirescore/NoOverlapKFold.py
xirescore/XiRescore.py
xirescore/__init__.py
xirescore/__main__.py
xirescore/_default_options.py
xirescore/_gui.py
xirescore/_version.py
xirescore/async_result_resolving.py
xirescore/cli.py
xirescore/column_generating.py
xirescore/df_serializing.py
xirescore/feature_extracting.py
xirescore/feature_scaling.py
xirescore/hyperparameter_optimizing.py
xirescore/imputing.py
xirescore/input_validating.py
xirescore/readers.py
xirescore/rescoring.py
xirescore/train_data_selecting.py
xirescore/training.py
xirescore/writers.py
xirescore/assets/xirescore_logo.ico
xirescore/assets/xirescore_logo.png
xirescore-1.0.0a24.dist-info/licenses/LICENSE
xirescore-1.0.0a24.dist-info/METADATA
xirescore-1.0.0a24.dist-info/WHEEL
xirescore-1.0.0a24.dist-info/entry_points.txt
xirescore-1.0.0a24.dist-info/top_level.txt
xirescore-1.0.0a24.dist-info/RECORD
