Metadata-Version: 2.4
Name: xirescore
Version: 1.0.0a24
Summary: A corss-link mass spectrometry rescoring tool
Home-page: https://github.com/Rappsilber-Laboratory/xiRescore
Author: Falk Boudewijn Schimweg
Author-email: "Falk B. Schimweg" <git@falk.schimweg.de>
License: GNU Affero General Public License v3 or later (AGPLv3+)
Project-URL: Homepage, https://github.com/Rappsilber-Laboratory/xiRescore
Project-URL: Issues, https://github.com/Rappsilber-Laboratory/xiRescore/issues
Project-URL: Documentation, https://xirescore.readthedocs.io/
Keywords: proteomics,rescoring,crosslink,mass spectrometry
Classifier: Development Status :: 2 - Pre-Alpha
Classifier: Intended Audience :: Developers
Classifier: License :: OSI Approved :: GNU Affero General Public License v3 or later (AGPLv3+)
Classifier: Natural Language :: English
Classifier: Programming Language :: Python :: 3
Classifier: Programming Language :: Python :: 3.9
Classifier: Programming Language :: Python :: 3.10
Classifier: Programming Language :: Python :: 3.11
Classifier: Programming Language :: Python :: 3.12
Requires-Python: >=3.9
License-File: LICENSE
Requires-Dist: frosch~=0.1.9
Requires-Dist: pandas>=2.0.0
Requires-Dist: numpy>=1.7.2
Requires-Dist: PyYAML~=6.0
Requires-Dist: tabulate~=0.9.0
Requires-Dist: numpy-indexed~=0.3.7
Requires-Dist: scikit-learn>=1.3.2
Requires-Dist: joblib~=1.2.0
Requires-Dist: xgboost~=1.7.5
Requires-Dist: tqdm~=4.66.0
Requires-Dist: hyperopt~=0.2.7
Requires-Dist: lightgbm~=3.3.5
Requires-Dist: imblearn~=0.0
Requires-Dist: py~=1.11.0
Requires-Dist: networkx>=2.8
Requires-Dist: multiprocess~=0.70.16
Requires-Dist: threadpoolctl>=3.5.0
Requires-Dist: deepmerge~=1.1.0
Requires-Dist: SQLAlchemy~=2.0.30
Requires-Dist: psycopg2>=2.9
Requires-Dist: python-logging-loki
Requires-Dist: fastparquet>=2022.11.0
Requires-Dist: pyarrow<16; sys_platform == "win32"
Requires-Dist: pyarrow; sys_platform != "win32"
Requires-Dist: scipy>=1.0.1
Requires-Dist: setuptools
Requires-Dist: xiutilities~=1.2.3
Requires-Dist: polars
Requires-Dist: xifdr
Dynamic: author
Dynamic: classifier
Dynamic: home-page
Dynamic: license-file
Dynamic: requires-dist
Dynamic: requires-python
